scikit_lite-0.0.1.dist-info/METADATA
scikit_lite-0.0.1.dist-info/WHEEL
scikit_lite-0.0.1.dist-info/licenses/LICENSE
sklite/__init__.py
sklite/_core.cpython-311-darwin.so
sklite/base.py
sklite/cluster/__init__.py
sklite/cluster/kmeans.py
sklite/linear_model/__init__.py
sklite/linear_model/_base.py
sklite/linear_model/linear_regression.py
sklite/linear_model/logistic_regression.py
sklite/metrics/__init__.py
sklite/metrics/classification.py
sklite/metrics/regression.py
scikit_lite-0.0.1.dist-info/RECORD
