Metadata-Version: 2.4
Name: scikit-lite
Version: 0.0.1
Classifier: Development Status :: 2 - Pre-Alpha
Classifier: Intended Audience :: Developers
Classifier: Intended Audience :: Science/Research
Classifier: License :: OSI Approved :: MIT License
Classifier: Operating System :: OS Independent
Classifier: Programming Language :: Python :: 3
Classifier: Programming Language :: Python :: 3.11
Classifier: Programming Language :: Python :: 3.12
Classifier: Topic :: Scientific/Engineering
Classifier: Topic :: Scientific/Engineering :: Artificial Intelligence
Classifier: Topic :: Software Development :: Libraries :: Python Modules
Requires-Dist: numpy>=2.3.5
Requires-Dist: maturin>=1.10.2 ; extra == 'dev'
Requires-Dist: pre-commit>=4.5.0 ; extra == 'dev'
Requires-Dist: pytest>=7.0.0 ; extra == 'dev'
Requires-Dist: ruff>=0.14.8 ; extra == 'dev'
Provides-Extra: dev
License-File: LICENSE
Summary: Lightweight machine learning library with scikit-learn compatible API
Keywords: machine-learning,scikit-learn,numpy,linear-regression,ml,data-science
Author: scikit-lite contributors
Maintainer: scikit-lite contributors
License: MIT
Requires-Python: >=3.11
Project-URL: Homepage, https://github.com/kowanietz/scikit-lite
Project-URL: Repository, https://github.com/kowanietz/scikit-lite
Project-URL: Issues, https://github.com/kowanietz/scikit-lite/issues
